tributaries/Central.py
tributaries/README.md
tributaries/SafePass.py
tributaries/Sweeps.py
tributaries/VPN.py
tributaries/__init__.py
tributaries/Examples/Servers/Bluehive.py
tributaries/Examples/Servers/Minimal.py
tributaries/Examples/Servers/XuLab.py
tributaries/Examples/Servers/XuLabAdvanced.py
tributaries/Examples/Sweeps/Bittle.py
tributaries/Examples/Sweeps/ImageNet-mini.py
tributaries/Examples/Sweeps/ImageNet.py
tributaries/Examples/Sweeps/Pong.py
tributaries/Examples/Sweeps/XRDsPaper.py
tributaries/Examples/Sweeps/XRDsPaperBluehive.py
tributaries_ml-1.0.5.dist-info/METADATA
tributaries_ml-1.0.5.dist-info/WHEEL
tributaries_ml-1.0.5.dist-info/entry_points.txt
tributaries_ml-1.0.5.dist-info/top_level.txt
tributaries_ml-1.0.5.dist-info/RECORD
