Metadata-Version: 2.1
Name: tributaries-ml
Version: 1.0.5
Summary: A library for mass-deploying UnifiedML apps on slurm-enabled servers.
Home-page: https://github.com/agi-init/tributaries
Author: Sam Lerman
Author-email: agi.init@gmail.com
Project-URL: Bug Tracker, https://github.com/agi-init/tributaries/issues
Keywords: slurm,job scheduling,DRM,artificial intelligence,machine learning,deep learning,reinforcement learning,image classification
Classifier: Programming Language :: Python
Classifier: License :: OSI Approved :: MIT License
Classifier: Operating System :: OS Independent
Requires-Python: >=3.10.8
Requires-Dist: pexpect (==4.8.0)
Requires-Dist: cryptography (>=39.0.0)
Requires-Dist: UnifiedML (==1.0.6)
